aiposematic/__init__.py
aiposematic-0.3.dist-info/licenses/LICENSE
aiposematic-0.3.dist-info/WHEEL
aiposematic-0.3.dist-info/METADATA
aiposematic-0.3.dist-info/RECORD
