Metadata-Version: 2.4
Name: aiposematic
Version: 0.3
Summary: Aiposematic: Scramble & Recover using image key + operation string , By: Fibo Metavinci
Author-email: Fibo Metavinci <pszdw-75nat-5227i-bha5s-y7lai-pebdq-o2agp-3xho4-hd6z6-emxrd-nqe@dmail.ai>
License-Expression: MIT
License-File: LICENSE
Requires-Dist: colorama>=0.4.6
Requires-Dist: contourpy>=1.3.3
Requires-Dist: cycler>=0.12.1
Requires-Dist: fonttools>=4.60.1
Requires-Dist: imageio>=2.37.2
Requires-Dist: kiwisolver>=1.4.9
Requires-Dist: lazy-loader>=0.4
Requires-Dist: matplotlib>=3.10.7
Requires-Dist: networkx>=3.5
Requires-Dist: numpy>=2.3.4
Requires-Dist: opencv-python>=4.11.0.86
Requires-Dist: packaging>=25.0
Requires-Dist: pillow>=12.0.0
Requires-Dist: pyparsing>=3.2.5
Requires-Dist: python-dateutil>=2.9.0.post0
Requires-Dist: qrcode>=8.2
Requires-Dist: scikit-image>=0.25.2
Requires-Dist: scipy>=1.16.3
Requires-Dist: six>=1.17.0
Requires-Dist: tifffile>=2025.10.16
Project-URL: Home, https://github.com/inviti8/aiposematic
